{
    "author": "95度茅台",
    "scriptable": true,
    "icon": "https://gitcode.net/4qiao/framework/raw/master/img/icon/4qiao.png",
    "repo": "https://gitcode.net/4qiao/scriptable",
    "apps": [
        {
            "depend": {
                "name": "DmYY",
                "scriptURL": "https://raw.githubusercontent.com/dompling/Scriptable/master/Scripts/DmYY.js"
            },
            "title": "交管12123",
            "thumb": "https://gitcode.net/4qiao/framework/raw/master/img/icon/12123.png",
            "version": "1.0.0",
            "description": "支付宝小程序交管12123",
            "scriptURL": "https://gitcode.net/4qiao/scriptable/raw/master/api/violation.js",
            "name": "交管12123"
        },
        {
            "depend": {
                "name": "DmYY",
                "scriptURL": "https://raw.githubusercontent.com/dompling/Scriptable/master/Scripts/DmYY.js"
            },
            "title": "全国油价",
            "thumb": "https://gitcode.net/4qiao/framework/raw/master/img/icon/map.gif",
            "version": "1.0.0",
            "description": "查看全国油价预警",
            "scriptURL": "https://gitcode.net/4qiao/scriptable/raw/master/api/oils.js",
            "name": "全国油价"
        },
        {
            "depend": {
                "name": "DmYY",
                "scriptURL": "https://raw.githubusercontent.com/dompling/Scriptable/master/Scripts/DmYY.js"
            },
            "title": "中国电信",
            "thumb": "https://gitcode.net/4qiao/framework/raw/master/img/icon/telecom.png",
            "version": "1.0.0",
            "description": "中国电信余量",
            "scriptURL": "https://gitcode.net/4qiao/scriptable/raw/master/api/telecom.js",
            "name": "中国电信"
        },
        {
            "depend": {
                "name": "DmYY",
                "scriptURL": "https://raw.githubusercontent.com/dompling/Scriptable/master/Scripts/DmYY.js"
            },
            "title": "南网在线",
            "thumb": "https://gitcode.net/4qiao/framework/raw/master/img/icon/electric.png",
            "version": "1.0.0",
            "description": "南网在线App",
            "scriptURL": "https://gitcode.net/4qiao/scriptable/raw/master/api/electric.js",
            "name": "南网在线"
        },
        {
            "depend": {
                "name": "DmYY",
                "scriptURL": "https://raw.githubusercontent.com/dompling/Scriptable/master/Scripts/DmYY.js"
            },
            "title": "负一屏底栏",
            "thumb": "https://gitcode.net/4qiao/framework/raw/master/img/icon/bottom.png",
            "version": "1.0.0",
            "description": "iOS16负一屏底栏",
            "scriptURL": "https://gitcode.net/4qiao/scriptable/raw/master/api/bottomBar.js",
            "name": "负一屏底栏"
        },
        {
            "depend": {
                "name": "DmYY",
                "scriptURL": "https://raw.githubusercontent.com/dompling/Scriptable/master/Scripts/DmYY.js"
            },
            "title": "透明背景",
            "thumb": "https://gitcode.net/4qiao/framework/raw/master/img/icon/bg.png",
            "version": "1.0.0",
            "description": "代码来源于网络，提供给需要的用户制作透明背景",
            "scriptURL": "https://gitcode.net/4qiao/scriptable/raw/master/api/background.js",
            "name": "透明背景"
        },
        {
            "depend": {
                "name": "DmYY",
                "scriptURL": "https://raw.githubusercontent.com/dompling/Scriptable/master/Scripts/DmYY.js"
            },
            "title": "随机组件",
            "thumb": "https://sweixinfile.hisense.com/media/M00/72/0C/Ch4FyGOJXYyAAMXRACR6Kf6RXAc227.gif",
            "version": "1.0.0",
            "description": "随机切换多个小组件",
            "scriptURL": "https://gitcode.net/4qiao/scriptable/raw/master/api/randomScript.js",
            "name": "随机组件"
        }
    ]
}